Workbook
Name Slicer_Brand: #N/A
Name Slicer_Category: #N/A

Sheet Myntra_Fashion_Sales_5000
A1: Order_ID | B1: Product_ID | C1: Brand | D1: Category | E1: Gender | F1: Original_Price | G1: Discount_Pct | H1: Selling_Price | I1: Rating | J1: Reviews | K1: Quantity | L1: Sales | M1: Order_Date | N1: State
A2: ORD100000 | B2: PROD2824A | C2: Zara | D2: Jeans | E2: Men | F2: 2559 | G2: 30 | H2: 1791 | I2: 4.3 | J2: 240 | K2: 2 | L2: 3582 | M2: 45850 | N2: Karnataka
A3: ORD100001 | B3: PROD7912A | C3: Nike | D3: Kurtas | E3: Men | F3: 3234 | G3: 25 | H3: 2426 | I3: 4 | J3: 137 | K3: 1 | L3: 2426 | M3: 45957 | N3: Chhattisgarh
A4: ORD100002 | B4: PROD7873B | C4: Manyavar | D4: Sarees | E4: Men | F4: 6709 | G4: 20 | H4: 5367 | I4: 4 | J4: 25 | K4: 1 | L4: 5367 | M4: 45636 | N4: Tamil Nadu
A5: ORD100003 | B5: PROD2519D | C5: Puma | D5: Shirts | E5: Women | F5: 3262 | G5: 15 | H5: 2773 | I5: 4 | J5: 303 | K5: 2 | L5: 5546 | M5: 45841 | N5: Tamil Nadu
A6: ORD100004 | B6: PROD7201A | C6: Adidas | D6: Sarees | E6: Women | F6: 6862 | G6: 15 | H6: 5833 | I6: 4.9 | J6: 7 | K6: 1 | L6: 5833 | M6: 45525 | N6: Kerala
A7: ORD100005 | B7: PROD2307B | C7: Puma | D7: Leggings | E7: Women | F7: 2247 | G7: 25 | H7: 1685 | I7: 4.5 | J7: 548 | K7: 1 | L7: 1685 | M7: 45655 | N7: Gujarat
A8: ORD100006 | B8: PROD5374A | C8: Fabindia | D8: Shoes | E8: Women | F8: 4167 | G8: 20 | H8: 3334 | I8: 3.9 | J8: 47 | K8: 5 | L8: 16670 | M8: 45947 | N8: Chhattisgarh
A9: ORD100007 | B9: PROD4598C | C9: Nike | D9: Jeans | E9: Men | F9: 4288 | G9: 20 | H9: 3430 | I9: 4.4 | J9: 34 | K9: 1 | L9: 3430 | M9: 45872 | N9: Madhya Pradesh
A10: ORD100008 | B10: PROD4483D | C10: Biba | D10: Dresses | E10: Women | F10: 2959 | G10: 10 | H10: 2663 | I10: 4.2 | J10: 131 | K10: 1 | L10: 2663 | M10: 45561 | N10: Jharkhand
A11: ORD100009 | B11: PROD8019D | C11: H&M | D11: Jeans | E11: Men | F11: 5164 | G11: 20 | H11: 4131 | I11: 3.1 | J11: 99 | K11: 1 | L11: 4131 | M11: 45404 | N11: West Bengal
A12: ORD100010 | B12: PROD3621D | C12: Fabindia | D12: Kurtas | E12: Women | F12: 3916 | G12: 25 | H12: 2937 | I12: 3.6 | J12: 80 | K12: 1 | L12: 2937 | M12: 45858 | N12: Maharashtra
A13: ORD100011 | B13: PROD2876C | C13: H&M | D13: Kurtas | E13: Women | F13: 4351 | G13: 15 | H13: 3698 | I13: 4.3 | J13: 68 | K13: 4 | L13: 14792 | M13: 45561 | N13: Assam
... A5001: ORD104999 | B5001: PROD9046C | C5001: Zara | D5001: Shirts | E5001: Women | F5001: 4413 | G5001: 30 | H5001: 3089 | I5001: 4.2 | J5001: 77 | K5001: 3 | L5001: 9267 | M5001: 45511 | N5001: Maharashtra

Sheet Cleaned Sheet
A1: Order_ID | B1: Product_ID | C1: Brand | D1: Category | E1: Gender | F1: Original_Price | G1: Discount_Pct | H1: Selling_Price | I1: Rating | J1: Reviews | K1: Quantity | L1: Sales | M1: Order_Date | N1: State
A2: ORD100000 | B2: PROD2824A | C2: Zara | D2: Jeans | E2: Men | F2: 2559 | G2: 30 | H2: 1791 | I2: 4.3 | J2: 240 | K2: 2 | L2: 3582 | M2: 45850 | N2: Karnataka
A3: ORD100001 | B3: PROD7912A | C3: Nike | D3: Kurtas | E3: Men | F3: 3234 | G3: 25 | H3: 2426 | I3: 4 | J3: 137 | K3: 1 | L3: 2426 | M3: 45957 | N3: Chhattisgarh
A4: ORD100002 | B4: PROD7873B | C4: Manyavar | D4: Sarees | E4: Men | F4: 6709 | G4: 20 | H4: 5367 | I4: 4 | J4: 25 | K4: 1 | L4: 5367 | M4: 45636 | N4: Tamil Nadu
A5: ORD100003 | B5: PROD2519D | C5: Puma | D5: Shirts | E5: Women | F5: 3262 | G5: 15 | H5: 2773 | I5: 4 | J5: 303 | K5: 2 | L5: 5546 | M5: 45841 | N5: Tamil Nadu
A6: ORD100004 | B6: PROD7201A | C6: Adidas | D6: Sarees | E6: Women | F6: 6862 | G6: 15 | H6: 5833 | I6: 4.9 | J6: 7 | K6: 1 | L6: 5833 | M6: 45525 | N6: Kerala
A7: ORD100005 | B7: PROD2307B | C7: Puma | D7: Leggings | E7: Women | F7: 2247 | G7: 25 | H7: 1685 | I7: 4.5 | J7: 548 | K7: 1 | L7: 1685 | M7: 45655 | N7: Gujarat
A8: ORD100006 | B8: PROD5374A | C8: Fabindia | D8: Shoes | E8: Women | F8: 4167 | G8: 20 | H8: 3334 | I8: 3.9 | J8: 47 | K8: 5 | L8: 16670 | M8: 45947 | N8: Chhattisgarh
A9: ORD100007 | B9: PROD4598C | C9: Nike | D9: Jeans | E9: Men | F9: 4288 | G9: 20 | H9: 3430 | I9: 4.4 | J9: 34 | K9: 1 | L9: 3430 | M9: 45872 | N9: Madhya Pradesh
A10: ORD100008 | B10: PROD4483D | C10: Biba | D10: Dresses | E10: Women | F10: 2959 | G10: 10 | H10: 2663 | I10: 4.2 | J10: 131 | K10: 1 | L10: 2663 | M10: 45561 | N10: Jharkhand
A11: ORD100009 | B11: PROD8019D | C11: H&M | D11: Jeans | E11: Men | F11: 5164 | G11: 20 | H11: 4131 | I11: 3.1 | J11: 99 | K11: 1 | L11: 4131 | M11: 45404 | N11: West Bengal
A12: ORD100010 | B12: PROD3621D | C12: Fabindia | D12: Kurtas | E12: Women | F12: 3916 | G12: 25 | H12: 2937 | I12: 3.6 | J12: 80 | K12: 1 | L12: 2937 | M12: 45858 | N12: Maharashtra
A13: ORD100011 | B13: PROD2876C | C13: H&M | D13: Kurtas | E13: Women | F13: 4351 | G13: 15 | H13: 3698 | I13: 4.3 | J13: 68 | K13: 4 | L13: 14792 | M13: 45561 | N13: Assam
... A5001: ORD104999 | B5001: PROD9046C | C5001: Zara | D5001: Shirts | E5001: Women | F5001: 4413 | G5001: 30 | H5001: 3089 | I5001: 4.2 | J5001: 77 | K5001: 3 | L5001: 9267 | M5001: 45511 | N5001: Maharashtra

Sheet Day 1 -XLOOKUP,VLOOKUP
A1: XLOOKUP | E1: XLOOKUP: The modern, flexible replacement for VLOOKUP and HLOOKUP that can search in any direction (left, right, up, or down) and defaults to exact matches.
A2: ProductID | B2: Brand | C2: Selling Price
A3: PROD1697C | B3: =_xlfn.XLOOKUP(A3,Myntra_Fashion_Sales_5000!B3:B5002,Myntra_Fashion_Sales_5000!C3:C5002,"NOT FOUND") -> Nike | C3: {=_xlfn.XLOOKUP(A3,Myntra_Fashion_Sales_5000!B3:B5002,Myntra_Fashion_Sales_5000!H3:H5002,NOTFOUND)} -> 1766
A4: PROD2621C | B4: =_xlfn.XLOOKUP(A4,Myntra_Fashion_Sales_5000!B4:B5003,Myntra_Fashion_Sales_5000!C4:C5003,"NOT FOUND") -> Fabindia | C4: =_xlfn.XLOOKUP(A4,Myntra_Fashion_Sales_5000!B4:B5003,Myntra_Fashion_Sales_5000!H4:H5003,"NOT FOUND") -> 2557 | E4: • Syntax: =XLOOKUP(lookup_value, lookup_array, return_array, [if_not_found], [match_mode], [search_mode])
E6: =XLOOKUP(what,search_column,return_column,NOTFOUND)
A7: VLOOKUP
A8: ProductID | B8: Brand | C8: Selling Price
A9: PROD1697C | B9: =VLOOKUP(A9,Myntra_Fashion_Sales_5000!B3:H5001,2,"FALSE") -> Nike | C9: =VLOOKUP(A9,Myntra_Fashion_Sales_5000!B2:H5001,7,FALSE) -> 1766 | E9: VLOOKUP (Vertical Lookup): Searches down the first column of a table and returns a value from a specified column to the right.
A10: PROD2621C | B10: =VLOOKUP(A10,Myntra_Fashion_Sales_5000!B4:H5002,2,"FALSE") -> Fabindia | C10: =VLOOKUP(A10,Myntra_Fashion_Sales_5000!B3:H5002,7,FALSE) -> 2557
E12: • Syntax: =VLOOKUP(lookup_value, table_array, col_index_num, [range_lookup]
E14: =VLOOKUP(what,where,col_number,FALSE)

Sheet Day 2-PivotTable +Dashboard
A6: Row Labels | B6: Sum of Selling_Price
A7: Zara | B7: 1612626
A8: Adidas | B8: 1506147
A9: Roadster | B9: 1427667
A10: Levis | B10: 1417920
A11: Nike | B11: 1395442
A12: Fabindia | B12: 1347264
A13: Puma | B13: 1256253
A14: Biba | B14: 1241554
A15: H&M | B15: 1212420
A16: Manyavar | B16: 1181975
A17: Grand Total | B17: 13599268

Sheet Day 3 -Profit Calculation
A1: Order_ID | B1: Product_ID | C1: Brand | D1: Category | E1: Gender | F1: Original_Price | G1: Discount_Pct | H1: Selling_Price | I1: Rating | J1: Reviews | K1: Quantity | L1: Sales | M1: Order_Date | N1: State | O1: Discount_Amount | P1: Cost_Price(Assumed 60%) | Q1: Profit
A2: ORD100000 | B2: PROD2824A | C2: Zara | D2: Jeans | E2: Men | F2: 2559 | G2: 30 | H2: 1791 | I2: 4.3 | J2: 240 | K2: 2 | L2: 3582 | M2: 45850 | N2: Karnataka | O2: =F2-H2 -> 768 | P2: =F2*0.6 -> 1535.4 | Q2: =(H2-P2)*K2 -> 511.2
A3: ORD100001 | B3: PROD7912A | C3: Nike | D3: Kurtas | E3: Men | F3: 3234 | G3: 25 | H3: 2426 | I3: 4 | J3: 137 | K3: 1 | L3: 2426 | M3: 45957 | N3: Chhattisgarh | O3: =F3-H3 -> 808 | P3: =F3*0.6 -> 1940.4 | Q3: =(H3-P3)*K3 -> 485.6
A4: ORD100002 | B4: PROD7873B | C4: Manyavar | D4: Sarees | E4: Men | F4: 6709 | G4: 20 | H4: 5367 | I4: 4 | J4: 25 | K4: 1 | L4: 5367 | M4: 45636 | N4: Tamil Nadu | O4: =F4-H4 -> 1342 | P4: =F4*0.6 -> 4025.4 | Q4: =(H4-P4)*K4 -> 1341.6
A5: ORD100003 | B5: PROD2519D | C5: Puma | D5: Shirts | E5: Women | F5: 3262 | G5: 15 | H5: 2773 | I5: 4 | J5: 303 | K5: 2 | L5: 5546 | M5: 45841 | N5: Tamil Nadu | O5: =F5-H5 -> 489 | P5: =F5*0.6 -> 1957.2 | Q5: =(H5-P5)*K5 -> 1631.6
A6: ORD100004 | B6: PROD7201A | C6: Adidas | D6: Sarees | E6: Women | F6: 6862 | G6: 15 | H6: 5833 | I6: 4.9 | J6: 7 | K6: 1 | L6: 5833 | M6: 45525 | N6: Kerala | O6: =F6-H6 -> 1029 | P6: =F6*0.6 -> 4117.2 | Q6: =(H6-P6)*K6 -> 1715.8
A7: ORD100005 | B7: PROD2307B | C7: Puma | D7: Leggings | E7: Women | F7: 2247 | G7: 25 | H7: 1685 | I7: 4.5 | J7: 548 | K7: 1 | L7: 1685 | M7: 45655 | N7: Gujarat | O7: =F7-H7 -> 562 | P7: =F7*0.6 -> 1348.2 | Q7: =(H7-P7)*K7 -> 336.8
A8: ORD100006 | B8: PROD5374A | C8: Fabindia | D8: Shoes | E8: Women | F8: 4167 | G8: 20 | H8: 3334 | I8: 3.9 | J8: 47 | K8: 5 | L8: 16670 | M8: 45947 | N8: Chhattisgarh | O8: =F8-H8 -> 833 | P8: =F8*0.6 -> 2500.2 | Q8: =(H8-P8)*K8 -> 4169
A9: ORD100007 | B9: PROD4598C | C9: Nike | D9: Jeans | E9: Men | F9: 4288 | G9: 20 | H9: 3430 | I9: 4.4 | J9: 34 | K9: 1 | L9: 3430 | M9: 45872 | N9: Madhya Pradesh | O9: =F9-H9 -> 858 | P9: =F9*0.6 -> 2572.8 | Q9: =(H9-P9)*K9 -> 857.2
A10: ORD100008 | B10: PROD4483D | C10: Biba | D10: Dresses | E10: Women | F10: 2959 | G10: 10 | H10: 2663 | I10: 4.2 | J10: 131 | K10: 1 | L10: 2663 | M10: 45561 | N10: Jharkhand | O10: =F10-H10 -> 296 | P10: =F10*0.6 -> 1775.4 | Q10: =(H10-P10)*K10 -> 887.6
A11: ORD100009 | B11: PROD8019D | C11: H&M | D11: Jeans | E11: Men | F11: 5164 | G11: 20 | H11: 4131 | I11: 3.1 | J11: 99 | K11: 1 | L11: 4131 | M11: 45404 | N11: West Bengal | O11: =F11-H11 -> 1033 | P11: =F11*0.6 -> 3098.4 | Q11: =(H11-P11)*K11 -> 1032.6
A12: ORD100010 | B12: PROD3621D | C12: Fabindia | D12: Kurtas | E12: Women | F12: 3916 | G12: 25 | H12: 2937 | I12: 3.6 | J12: 80 | K12: 1 | L12: 2937 | M12: 45858 | N12: Maharashtra | O12: =F12-H12 -> 979 | P12: =F12*0.6 -> 2349.6 | Q12: =(H12-P12)*K12 -> 587.4
A13: ORD100011 | B13: PROD2876C | C13: H&M | D13: Kurtas | E13: Women | F13: 4351 | G13: 15 | H13: 3698 | I13: 4.3 | J13: 68 | K13: 4 | L13: 14792 | M13: 45561 | N13: Assam | O13: =F13-H13 -> 653 | P13: =F13*0.6 -> 2610.6 | Q13: =(H13-P13)*K13 -> 4349.6
... A5001: ORD104999 | B5001: PROD9046C | C5001: Zara | D5001: Shirts | E5001: Women | F5001: 4413 | G5001: 30 | H5001: 3089 | I5001: 4.2 | J5001: 77 | K5001: 3 | L5001: 9267 | M5001: 45511 | N5001: Maharashtra | O5001: =F5001-H5001 -> 1324 | P5001: =F5001*0.6 -> 2647.8 | Q5001: =(H5001-P5001)*K5001 -> 1323.6

Sheet Day 4-Profit Dashboard
A6: Row Labels | B6: Sum of Profit
A7: Zara | B7: 502267.4
A8: Adidas | B8: 459945.8
A9: Levis | B9: 454481.4
A10: Roadster | B10: 439621.2
A11: Fabindia | B11: 423471.6
A12: Nike | B12: 421229
A13: Manyavar | B13: 365504
A14: H&M | B14: 350948.2
A15: Biba | B15: 350527.6
A16: Puma | B16: 347429.2
A17: Grand Total | B17: 4115425.4

Sheet Formula Practice
A1: Order_ID | B1: Product_ID | C1: Brand | D1: Category | E1: Gender | F1: Original_Price | G1: Discount_Pct | H1: Selling_Price | I1: Rating | J1: Reviews | K1: Quantity | L1: Sales | M1: Order_Date | N1: State | O1: Date in TEXT | P1: Year | Q1: Quarter | R1: sumif(where to check,what to find,what to add) | S1: sumifs(what to add,where to check,what to find,where to check,what to find)---many conditions | T1: How are Sales
A2: ORD100000 | B2: PROD2824A | C2: Zara | D2: Jeans | E2: Men | F2: 2559 | G2: 30 | H2: 1791 | I2: 4.3 | J2: 240 | K2: 2 | L2: 3582 | M2: 45850 | N2: Karnataka | O2: =TEXT(M2,"MMM-YYYY") -> Jul-2025 | P2: =YEAR(M2) -> 2025 | Q2: =CHOOSE(MONTH(M2),1,1,1,1,2,2,2,2,3,3,3,3,4,4,4,4) -> 2 | R2: =SUMIF(C2:C5001,"Nike",L2:L5001) -> 2178812 | S2: =SUMIFS(L2:L5001,C2:C5001,"Nike",N2:N5001,"Delhi") -> 121366 | T2: =IF(L2>5000,"High Sales","Low Sales") -> Low Sales | V2: =SUMIFS(L2:L5001,Q2:Q5001,1,P2:P5001,2025) -> 3255358
A3: ORD100001 | B3: PROD7912A | C3: Nike | D3: Kurtas | E3: Men | F3: 3234 | G3: 25 | H3: 2426 | I3: 4 | J3: 137 | K3: 1 | L3: 2426 | M3: 45957 | N3: Chhattisgarh | O3: =TEXT(M3,"MMM-YYYY") -> Oct-2025 | P3: =YEAR(M3) -> 2025 | Q3: =CHOOSE(MONTH(M3),1,1,1,1,2,2,2,2,3,3,3,3,4,4,4,4) -> 3 | T3: =IF(L3>5000,"High Sales","Low Sales") -> Low Sales | V3: =SUMIFS(L2:L5001,P2:P5001,2025) -> 10430076
A4: ORD100002 | B4: PROD7873B | C4: Manyavar | D4: Sarees | E4: Men | F4: 6709 | G4: 20 | H4: 5367 | I4: 4 | J4: 25 | K4: 1 | L4: 5367 | M4: 45636 | N4: Tamil Nadu | O4: =TEXT(M4,"MMM-YYYY") -> Dec-2024 | P4: =YEAR(M4) -> 2024 | Q4: =CHOOSE(MONTH(M4),1,1,1,1,2,2,2,2,3,3,3,3,4,4,4,4) -> 3 | T4: =IF(L4>5000,"High Sales","Low Sales") -> High Sales | U4: Max Sales | V4: =MAX(L2:L5001) -> 45785 | W4: =_xlfn.XLOOKUP(V4,L2:L5001,C2:C5001) -> Zara | X4: =_xlfn.XLOOKUP(V4,L2:L5001,D2:D5001) -> Shoes
A5: ORD100003 | B5: PROD2519D | C5: Puma | D5: Shirts | E5: Women | F5: 3262 | G5: 15 | H5: 2773 | I5: 4 | J5: 303 | K5: 2 | L5: 5546 | M5: 45841 | N5: Tamil Nadu | O5: =TEXT(M5,"MMM-YYYY") -> Jul-2025 | P5: =YEAR(M5) -> 2025 | Q5: =CHOOSE(MONTH(M5),1,1,1,1,2,2,2,2,3,3,3,3,4,4,4,4) -> 2 | T5: =IF(L5>5000,"High Sales","Low Sales") -> High Sales | U5: Min Sales | V5: =MIN(L2:L5001) -> 146 | W5: =_xlfn.XLOOKUP(V5,L3:L5002,C3:C5002) -> Fabindia | X5: =_xlfn.XLOOKUP(V5,L3:L5002,D3:D5002) -> Leggings
A6: ORD100004 | B6: PROD7201A | C6: Adidas | D6: Sarees | E6: Women | F6: 6862 | G6: 15 | H6: 5833 | I6: 4.9 | J6: 7 | K6: 1 | L6: 5833 | M6: 45525 | N6: Kerala | O6: =TEXT(M6,"MMM-YYYY") -> Aug-2024 | P6: =YEAR(M6) -> 2024 | Q6: =CHOOSE(MONTH(M6),1,1,1,1,2,2,2,2,3,3,3,3,4,4,4,4) -> 2 | T6: =IF(L6>5000,"High Sales","Low Sales") -> High Sales
A7: ORD100005 | B7: PROD2307B | C7: Puma | D7: Leggings | E7: Women | F7: 2247 | G7: 25 | H7: 1685 | I7: 4.5 | J7: 548 | K7: 1 | L7: 1685 | M7: 45655 | N7: Gujarat | O7: =TEXT(M7,"MMM-YYYY") -> Dec-2024 | P7: =YEAR(M7) -> 2024 | Q7: =CHOOSE(MONTH(M7),1,1,1,1,2,2,2,2,3,3,3,3,4,4,4,4) -> 3 | T7: =IF(L7>5000,"High Sales","Low Sales") -> Low Sales
A8: ORD100006 | B8: PROD5374A | C8: Fabindia | D8: Shoes | E8: Women | F8: 4167 | G8: 20 | H8: 3334 | I8: 3.9 | J8: 47 | K8: 5 | L8: 16670 | M8: 45947 | N8: Chhattisgarh | O8: =TEXT(M8,"MMM-YYYY") -> Oct-2025 | P8: =YEAR(M8) -> 2025 | Q8: =CHOOSE(MONTH(M8),1,1,1,1,2,2,2,2,3,3,3,3,4,4,4,4) -> 3 | T8: =IF(L8>5000,"High Sales","Low Sales") -> High Sales
A9: ORD100007 | B9: PROD4598C | C9: Nike | D9: Jeans | E9: Men | F9: 4288 | G9: 20 | H9: 3430 | I9: 4.4 | J9: 34 | K9: 1 | L9: 3430 | M9: 45872 | N9: Madhya Pradesh | O9: =TEXT(M9,"MMM-YYYY") -> Aug-2025 | P9: =YEAR(M9) -> 2025 | Q9: =CHOOSE(MONTH(M9),1,1,1,1,2,2,2,2,3,3,3,3,4,4,4,4) -> 2 | T9: =IF(L9>5000,"High Sales","Low Sales") -> Low Sales
A10: ORD100008 | B10: PROD4483D | C10: Biba | D10: Dresses | E10: Women | F10: 2959 | G10: 10 | H10: 2663 | I10: 4.2 | J10: 131 | K10: 1 | L10: 2663 | M10: 45561 | N10: Jharkhand | O10: =TEXT(M10,"MMM-YYYY") -> Sep-2024 | P10: =YEAR(M10) -> 2024 | Q10: =CHOOSE(MONTH(M10),1,1,1,1,2,2,2,2,3,3,3,3,4,4,4,4) -> 3 | T10: =IF(L10>5000,"High Sales","Low Sales") -> Low Sales
A11: ORD100009 | B11: PROD8019D | C11: H&M | D11: Jeans | E11: Men | F11: 5164 | G11: 20 | H11: 4131 | I11: 3.1 | J11: 99 | K11: 1 | L11: 4131 | M11: 45404 | N11: West Bengal | O11: =TEXT(M11,"MMM-YYYY") -> Apr-2024 | P11: =YEAR(M11) -> 2024 | Q11: =CHOOSE(MONTH(M11),1,1,1,1,2,2,2,2,3,3,3,3,4,4,4,4) -> 1 | T11: =IF(L11>5000,"High Sales","Low Sales") -> Low Sales
A12: ORD100010 | B12: PROD3621D | C12: Fabindia | D12: Kurtas | E12: Women | F12: 3916 | G12: 25 | H12: 2937 | I12: 3.6 | J12: 80 | K12: 1 | L12: 2937 | M12: 45858 | N12: Maharashtra | O12: =TEXT(M12,"MMM-YYYY") -> Jul-2025 | P12: =YEAR(M12) -> 2025 | Q12: =CHOOSE(MONTH(M12),1,1,1,1,2,2,2,2,3,3,3,3,4,4,4,4) -> 2 | T12: =IF(L12>5000,"High Sales","Low Sales") -> Low Sales
A13: ORD100011 | B13: PROD2876C | C13: H&M | D13: Kurtas | E13: Women | F13: 4351 | G13: 15 | H13: 3698 | I13: 4.3 | J13: 68 | K13: 4 | L13: 14792 | M13: 45561 | N13: Assam | O13: =TEXT(M13,"MMM-YYYY") -> Sep-2024 | P13: =YEAR(M13) -> 2024 | Q13: =CHOOSE(MONTH(M13),1,1,1,1,2,2,2,2,3,3,3,3,4,4,4,4) -> 3 | T13: =IF(L13>5000,"High Sales","Low Sales") -> High Sales
A14: ORD100012 | B14: PROD3927A | C14: Zara | D14: Jeans | E14: Men | F14: 4863 | G14: 30 | H14: 3404 | I14: 4.8 | J14: 67 | K14: 4 | L14: 13616 | M14: 45835 | N14: Maharashtra | O14: =TEXT(M14,"MMM-YYYY") -> Jun-2025 | P14: =YEAR(M14) -> 2025 | Q14: =CHOOSE(MONTH(M14),1,1,1,1,2,2,2,2,3,3,3,3,4,4,4,4) -> 2 | T14: =IF(L14>5000,"High Sales","Low Sales") -> High Sales
A15: ORD100013 | B15: PROD6310D | C15: Nike | D15: Kurtas | E15: Women | F15: 3970 | G15: 15 | H15: 3374 | I15: 4 | J15: 123 | K15: 3 | L15: 10122 | M15: 45372 | N15: Karnataka | O15: =TEXT(M15,"MMM-YYYY") -> Mar-2024 | P15: =YEAR(M15) -> 2024 | Q15: =CHOOSE(MONTH(M15),1,1,1,1,2,2,2,2,3,3,3,3,4,4,4,4) -> 1 | T15: =IF(L15>5000,"High Sales","Low Sales") -> High Sales
A16: ORD100014 | B16: PROD8962A | C16: Adidas | D16: Shoes | E16: Women | F16: 11132 | G16: 50 | H16: 5566 | I16: 3.8 | J16: 150 | K16: 1 | L16: 5566 | M16: 45913 | N16: Bihar | O16: =TEXT(M16,"MMM-YYYY") -> Sep-2025 | P16: =YEAR(M16) -> 2025 | Q16: =CHOOSE(MONTH(M16),1,1,1,1,2,2,2,2,3,3,3,3,4,4,4,4) -> 3 | T16: =IF(L16>5000,"High Sales","Low Sales") -> High Sales
A17: ORD100015 | B17: PROD4470B | C17: Zara | D17: Leggings | E17: Kids | F17: 2302 | G17: 20 | H17: 1842 | I17: 4.2 | J17: 61 | K17: 1 | L17: 1842 | M17: 45545 | N17: Rajasthan | O17: =TEXT(M17,"MMM-YYYY") -> Sep-2024 | P17: =YEAR(M17) -> 2024 | Q17: =CHOOSE(MONTH(M17),1,1,1,1,2,2,2,2,3,3,3,3,4,4,4,4) -> 3 | T17: =IF(L17>5000,"High Sales","Low Sales") -> Low Sales
... A5001: ORD104999 | B5001: PROD9046C | C5001: Zara | D5001: Shirts | E5001: Women | F5001: 4413 | G5001: 30 | H5001: 3089 | I5001: 4.2 | J5001: 77 | K5001: 3 | L5001: 9267 | M5001: 45511 | N5001: Maharashtra | O5001: =TEXT(M5001,"MMM-YYYY") -> Aug-2024 | P5001: =YEAR(M5001) -> 2024 | Q5001: =CHOOSE(MONTH(M5001),1,1,1,1,2,2,2,2,3,3,3,3,4,4,4,4) -> 2 | T5001: =IF(L5001>5000,"High Sales","Low Sales") -> High Sales
